pelmesha/Base_configs.yaml
pelmesha/__init__.py
pelmesha/align.py
pelmesha/loaders.py
pelmesha/pfeats.py
pelmesha/pspectra.py
pelmesha/utilities.py
pelmesha-0.4.0.dist-info/licenses/LICENSE.txt
pelmesha-0.4.0.dist-info/METADATA
pelmesha-0.4.0.dist-info/WHEEL
pelmesha-0.4.0.dist-info/top_level.txt
pelmesha-0.4.0.dist-info/RECORD
