Metadata-Version: 2.4
Name: pelmesha
Version: 0.4.0
Summary: A package for proccesing and aligning peaklist Mass-spectrometry imaging data from .imzml files
Author-email: Andrew Kuzin <Kuzya-90@bk.ru>
License-Expression: Apache-2.0
Project-URL: Homepage, https://github.com/Testudinata/pelmesha
Project-URL: Issues, https://github.com/Testudinata/pelmesha/issues
Classifier: Programming Language :: Python :: 3
Classifier: Operating System :: OS Independent
Classifier: Development Status :: 4 - Beta
Classifier: Intended Audience :: Science/Research
Requires-Python: >=3.8
License-File: LICENSE.txt
Requires-Dist: h5py
Requires-Dist: kdepy
Requires-Dist: matplotlib
Requires-Dist: numpy
Requires-Dist: pandas
Requires-Dist: pybaselines
Requires-Dist: pyimzML
Requires-Dist: scikit_learn
Requires-Dist: scipy
Requires-Dist: tqdm
Requires-Dist: PyYAML
Provides-Extra: dev
Requires-Dist: torch; extra == "dev"
Dynamic: license-file
